delta/__init__.py
delta/expr/__init__.py
delta/expr/expression.py
delta/lexer/__init__.py
delta/lexer/constants.py
delta/lexer/errors.py
delta/lexer/function.py
delta/lexer/lexer.py
delta/lexer/lexicalToken.py
delta/lexer/mathFunctions.py
delta/lexer/position.py
delta/lexer/tokenType.py
delta/lexer/tokens.py
delta/parser/__init__.py
delta/parser/errors.py
delta/parser/nodes.py
delta/parser/parser.py
delta_dx-0.1.2.dist-info/LICENSE
delta_dx-0.1.2.dist-info/METADATA
delta_dx-0.1.2.dist-info/WHEEL
delta_dx-0.1.2.dist-info/top_level.txt
delta_dx-0.1.2.dist-info/RECORD
