Metadata-Version: 2.1
Name: delta-dx
Version: 0.1.2
Summary: A Symbolic Differentiator
Home-page: https://github.com/MrRhuezzler/delta-dx
Author: MrRhuezzler
Author-email: anonymouspyro369@gmail.com
License: UNKNOWN
Project-URL: Bug Tracker, https://github.com/MrRhuezzler/delta-dx/issues
Platform: UNKNOWN
Classifier: Programming Language :: Python :: 3
Classifier: Programming Language :: Python :: 3.7
Classifier: License :: OSI Approved :: MIT License
Classifier: Operating System :: OS Independent
Requires-Python: >=3.7
License-File: LICENSE
